frequent/__init__.py
frequent/__version__.py
frequent/config.py
frequent/messaging.py
frequent/repository.py
frequent/singleton.py
frequent/unit_of_work.py
frequent-0.1.1.dist-info/LICENSE
frequent-0.1.1.dist-info/METADATA
frequent-0.1.1.dist-info/WHEEL
frequent-0.1.1.dist-info/top_level.txt
frequent-0.1.1.dist-info/RECORD
