Metadata-Version: 2.1
Name: frequent
Version: 0.1.1
Summary: Frequently used components for Python projects.
Home-page: https://www.github.com/douglasdaly/frequent-py
Author: Douglas Daly
Author-email: contact@douglasdaly.com
License: MIT
Project-URL: Source Code, https://www.github.com/douglasdaly/frequent-py
Project-URL: Documentation, https://frequent-py.readthedocs.io/
Platform: UNKNOWN
Classifier: Intended Audience :: Developers
Classifier: License :: OSI Approved :: MIT License
Classifier: Topic :: Software Development
Classifier: Topic :: Software Development :: Libraries :: Python Modules
Classifier: Topic :: Utilities
Classifier: Programming Language :: Python :: 3
Classifier: Programming Language :: Python :: 3.7
Requires-Python: >=3.5
Provides-Extra: test
Requires-Dist: pytest ; extra == 'test'
Requires-Dist: pytest-cov ; extra == 'test'
Requires-Dist: pytest-timeout ; extra == 'test'
Requires-Dist: pytest-xdist ; extra == 'test'
